moveread/pipelines/ocr/__init__.py
moveread/pipelines/ocr/__init__.pyi
moveread/pipelines/ocr/cli.py
moveread/pipelines/ocr/pipeline.py
moveread_pipelines_ocr-0.1.0.dist-info/METADATA
moveread_pipelines_ocr-0.1.0.dist-info/WHEEL
moveread_pipelines_ocr-0.1.0.dist-info/entry_points.txt
moveread_pipelines_ocr-0.1.0.dist-info/top_level.txt
moveread_pipelines_ocr-0.1.0.dist-info/RECORD
